{
    "snapshot": {
        "element": [
            {
                "path": "DiagnosticReport",
                "max": "*",
                "definition": "The findings and interpretation of diagnostic  tests performed on patients, groups of patients, devices, and locations, and/or specimens derived from these. The report includes clinical context such as requesting and provider information, and some mix of atomic results, images, textual and coded interpretations, and formatted representation of diagnostic reports.",
                "min": 0,
                "comments": "This is intended to capture a single report, and is not suitable for use in displaying summary information that covers multiple reports.  For example, this resource has not been designed for laboratory cumulative reporting formats nor detailed structured reports for sequencing.",
                "mapping": [
                    {
                        "identity": "v2",
                        "map": "ORU -> OBR"
                    },
                    {
                        "identity": "rim",
                        "map": "Observation[classCode=OBS, moodCode=EVN]"
                    },
                    {
                        "identity": "w5",
                        "map": "clinical.diagnostics"
                    }
                ],
                "short": "A Diagnostic report - a combination of request information, atomic results, images, interpretation, as well as formatted reports",
                "type": [
                    {
                        "code": "DomainResource"
                    }
                ],
                "alias": [
                    "Report",
                    "Test",
                    "Result",
                    "Results",
                    "Labs",
                    "Laboratory"
                ]
            },
            {
                "path": "DiagnosticReport.id",
                "max": "1",
                "definition": "The logical id of the resource, as used in the URL for the resource. Once assigned, this value never changes.",
                "min": 0,
                "comments": "The only time that a resource does not have an id is when it is being submitted to the server using a create operation. Bundles always have an id, though it is usually a generated UUID.",
                "short": "Logical id of this artifact",
                "type": [
                    {
                        "code": "id"
                    }
                ],
                "isSummary": true
            },
            {
                "path": "DiagnosticReport.meta",
                "max": "1",
                "definition": "The metadata about the resource. This is content that is maintained by the infrastructure. Changes to the content may not always be associated with version changes to the resource.",
                "min": 0,
                "type": [
                    {
                        "code": "Meta"
                    }
                ],
                "short": "Metadata about the resource",
                "isSummary": true
            },
            {
                "path": "DiagnosticReport.implicitRules",
                "max": "1",
                "definition": "A reference to a set of rules that were followed when the resource was constructed, and which must be understood when processing the content.",
                "min": 0,
                "comments": "Asserting this rule set restricts the content to be only understood by a limited set of trading partners. This inherently limits the usefulness of the data in the long term. However, the existing health eco-system is highly fractured, and not yet ready to define, collect, and exchange data in a generally computable sense. Wherever possible, implementers and/or specification writers should avoid using this element as much as possible.",
                "short": "A set of rules under which this content was created",
                "type": [
                    {
                        "code": "uri"
                    }
                ],
                "isSummary": true,
                "isModifier": true
            },
            {
                "path": "DiagnosticReport.language",
                "max": "1",
                "definition": "The base language in which the resource is written.",
                "min": 0,
                "comments": "Language is provided to support indexing and accessibility (typically, services such as text to speech use the language tag). The html language tag in the narrative applies  to the narrative. The language tag on the resource may be used to specify the language of other presentations generated from the data in the resource  Not all the content has to be in the base language. The Resource.language should not be assumed to apply to the narrative automatically. If a language is specified, it should it also be specified on the div element in the html (see rules in HTML5 for information about the relationship between xml:lang and the html lang attribute).",
                "short": "Language of the resource content",
                "type": [
                    {
                        "code": "code"
                    }
                ],
                "binding": {
                    "strength": "required",
                    "valueSetUri": "http://tools.ietf.org/html/bcp47",
                    "description": "A human language."
                }
            },
            {
                "path": "DiagnosticReport.text",
                "max": "1",
                "definition": "A human-readable narrative that contains a summary of the resource, and may be used to represent the content of the resource to a human. The narrative need not encode all the structured data, but is required to contain sufficient detail to make it \"clinically safe\" for a human to just read the narrative. Resource definitions may define what content should be represented in the narrative to ensure clinical safety.",
                "min": 0,
                "condition": [
                    "dom-1"
                ],
                "comments": "Contained resources do not have narrative. Resources that are not contained SHOULD have a narrative.",
                "mapping": [
                    {
                        "identity": "rim",
                        "map": "Act.text?"
                    }
                ],
                "short": "Text summary of the resource, for human interpretation",
                "type": [
                    {
                        "code": "Narrative"
                    }
                ],
                "alias": [
                    "narrative",
                    "html",
                    "xhtml",
                    "display"
                ]
            },
            {
                "path": "DiagnosticReport.contained",
                "max": "*",
                "definition": "These resources do not have an independent existence apart from the resource that contains them - they cannot be identified independently, and nor can they have their own independent transaction scope.",
                "min": 0,
                "comments": "This should never be done when the content can be identified properly, as once identification is lost, it is extremely difficult (and context dependent) to restore it again.",
                "mapping": [
                    {
                        "identity": "rim",
                        "map": "N/A"
                    }
                ],
                "short": "Contained, inline Resources",
                "type": [
                    {
                        "code": "Resource"
                    }
                ],
                "alias": [
                    "inline resources",
                    "anonymous resources",
                    "contained resources"
                ]
            },
            {
                "path": "DiagnosticReport.extension",
                "max": "*",
                "definition": "May be used to represent additional information that is not part of the basic definition of the resource. In order to make the use of extensions safe and manageable, there is a strict set of governance  applied to the definition and use of extensions. Though any implementer is allowed to define an extension, there is a set of requirements that SHALL be met as part of the definition of the extension.",
                "min": 0,
                "comments": "There can be no stigma associated with the use of extensions by any application, project, or standard - regardless of the institution or jurisdiction that uses or defines the extensions.  The use of extensions is what allows the FHIR specification to retain a core level of simplicity for everyone.",
                "mapping": [
                    {
                        "identity": "rim",
                        "map": "N/A"
                    }
                ],
                "short": "Additional Content defined by implementations",
                "type": [
                    {
                        "code": "Extension"
                    }
                ],
                "alias": [
                    "extensions",
                    "user content"
                ]
            },
            {
                "path": "DiagnosticReport.modifierExtension",
                "max": "*",
                "definition": "May be used to represent additional information that is not part of the basic definition of the resource, and that modifies the understanding of the element that contains it. Usually modifier elements provide negation or qualification. In order to make the use of extensions safe and manageable, there is a strict set of governance applied to the definition and use of extensions. Though any implementer is allowed to define an extension, there is a set of requirements that SHALL be met as part of the definition of the extension. Applications processing a resource are required to check for modifier extensions.",
                "min": 0,
                "isModifier": true,
                "comments": "There can be no stigma associated with the use of extensions by any application, project, or standard - regardless of the institution or jurisdiction that uses or defines the extensions.  The use of extensions is what allows the FHIR specification to retain a core level of simplicity for everyone.",
                "mapping": [
                    {
                        "identity": "rim",
                        "map": "N/A"
                    }
                ],
                "short": "Extensions that cannot be ignored",
                "type": [
                    {
                        "code": "Extension"
                    }
                ],
                "alias": [
                    "extensions",
                    "user content"
                ]
            },
            {
                "path": "DiagnosticReport.identifier",
                "max": "*",
                "definition": "The local ID assigned to the report by the order filler, usually by the Information System of the diagnostic service provider.",
                "min": 0,
                "requirements": "Need to know what identifier to use when making queries about this report from the source laboratory, and for linking to the report outside FHIR context.",
                "mapping": [
                    {
                        "identity": "v2",
                        "map": "OBR-51"
                    },
                    {
                        "identity": "rim",
                        "map": "id"
                    },
                    {
                        "identity": "w5",
                        "map": "id"
                    }
                ],
                "short": "Id for external references to this report",
                "type": [
                    {
                        "code": "Identifier"
                    }
                ],
                "isSummary": true,
                "alias": [
                    "ReportID"
                ]
            },
            {
                "path": "DiagnosticReport.status",
                "min": 1,
                "comments": "This is labeled as \"Is Modifier\" because applications need to take appropriate action if a report is withdrawn.",
                "short": "registered | partial | final | corrected | appended | cancelled | entered-in-error",
                "type": [
                    {
                        "code": "code"
                    }
                ],
                "binding": {
                    "strength": "required",
                    "description": "The status of the diagnostic report as a whole.",
                    "valueSetReference": {
                        "reference": "http://hl7.org/fhir/ValueSet/diagnostic-report-status"
                    }
                },
                "isSummary": true,
                "max": "1",
                "definition": "The status of the diagnostic report as a whole.",
                "mapping": [
                    {
                        "identity": "v2",
                        "map": "OBR-25 (not 1:1 mapping)"
                    },
                    {
                        "identity": "rim",
                        "map": "statusCode  Note: final and amended are distinguished by whether observation is the subject of a ControlAct event of type \"revise\""
                    },
                    {
                        "identity": "w5",
                        "map": "status"
                    }
                ],
                "requirements": "Diagnostic services routinely issue provisional/incomplete reports, and sometimes withdraw previously released reports.",
                "isModifier": true
            },
            {
                "path": "DiagnosticReport.category",
                "max": "1",
                "definition": "A code that classifies the clinical discipline, department or diagnostic service that created the report (e.g. cardiology, biochemistry, hematology, MRI). This is used for searching, sorting and display purposes.",
                "min": 0,
                "comments": "The level of granularity is defined by the category concepts in the value set. More fine-grained filtering can be performed using the metadata and/or terminology hierarchy in DiagnosticReport.code.",
                "mapping": [
                    {
                        "identity": "v2",
                        "map": "OBR-24"
                    },
                    {
                        "identity": "rim",
                        "map": "inboundRelationship[typeCode=COMP].source[classCode=LIST, moodCode=EVN, code < LabService].code"
                    },
                    {
                        "identity": "w5",
                        "map": "class"
                    }
                ],
                "short": "Service category",
                "type": [
                    {
                        "code": "CodeableConcept"
                    }
                ],
                "isSummary": true,
                "binding": {
                    "strength": "example",
                    "description": "Codes for diagnostic service sections.",
                    "valueSetReference": {
                        "reference": "http://hl7.org/fhir/ValueSet/diagnostic-service-sections"
                    }
                },
                "alias": [
                    "Department",
                    "Sub-department",
                    "service",
                    "discipline"
                ]
            },
            {
                "path": "DiagnosticReport.code",
                "max": "1",
                "definition": "A code or name that describes this diagnostic report.",
                "min": 1,
                "type": [
                    {
                        "code": "CodeableConcept"
                    }
                ],
                "mapping": [
                    {
                        "identity": "v2",
                        "map": "OBR-4 (HL7 v2 doesn't provide an easy way to indicate both the ordered test and the performed panel)"
                    },
                    {
                        "identity": "rim",
                        "map": "code"
                    },
                    {
                        "identity": "w5",
                        "map": "what"
                    }
                ],
                "short": "Name/Code for this diagnostic report",
                "isSummary": true,
                "binding": {
                    "strength": "preferred",
                    "description": "Codes that describe Diagnostic Reports.",
                    "valueSetReference": {
                        "reference": "http://hl7.org/fhir/ValueSet/report-codes"
                    }
                }
            },
            {
                "path": "DiagnosticReport.subject",
                "max": "1",
                "definition": "The subject of the report. Usually, but not always, this is a patient. However diagnostic services also perform analyses on specimens collected from a variety of other sources.",
                "min": 1,
                "requirements": "SHALL know the subject context.",
                "mapping": [
                    {
                        "identity": "v2",
                        "map": "PID-3 (no HL7 v2 mapping for Group or Device)"
                    },
                    {
                        "identity": "rim",
                        "map": "participation[typeCode=SBJ]"
                    },
                    {
                        "identity": "w5",
                        "map": "who.focus"
                    }
                ],
                "short": "The subject of the report, usually, but not always, the patient",
                "type": [
                    {
                        "code": "Reference",
                        "profile": [
                            "http://hl7.org/fhir/StructureDefinition/Patient"
                        ]
                    },
                    {
                        "code": "Reference",
                        "profile": [
                            "http://hl7.org/fhir/StructureDefinition/Group"
                        ]
                    },
                    {
                        "code": "Reference",
                        "profile": [
                            "http://hl7.org/fhir/StructureDefinition/Device"
                        ]
                    },
                    {
                        "code": "Reference",
                        "profile": [
                            "http://hl7.org/fhir/StructureDefinition/Location"
                        ]
                    }
                ],
                "isSummary": true,
                "alias": [
                    "Patient"
                ]
            },
            {
                "path": "DiagnosticReport.encounter",
                "max": "1",
                "definition": "The link to the health care event (encounter) when the order was made.",
                "min": 0,
                "type": [
                    {
                        "code": "Reference",
                        "profile": [
                            "http://hl7.org/fhir/StructureDefinition/Encounter"
                        ]
                    }
                ],
                "mapping": [
                    {
                        "identity": "v2",
                        "map": "PV1-19"
                    },
                    {
                        "identity": "rim",
                        "map": "inboundRelationship[typeCode=COMP].source[classCode=ENC, moodCode=EVN]"
                    },
                    {
                        "identity": "w5",
                        "map": "context"
                    }
                ],
                "short": "Health care event when test ordered",
                "isSummary": true
            },
            {
                "path": "DiagnosticReport.effective[x]",
                "max": "1",
                "type": [
                    {
                        "code": "dateTime"
                    },
                    {
                        "code": "Period"
                    }
                ],
                "definition": "The time or time-period the observed values are related to. When the subject of the report is a patient, this is usually either the time of the procedure or of specimen collection(s), but very often the source of the date/time is not known, only the date/time itself.",
                "min": 1,
                "requirements": "Need to know where in the patient history to file/present this report.",
                "mapping": [
                    {
                        "identity": "v2",
                        "map": "OBR-7"
                    },
                    {
                        "identity": "rim",
                        "map": "effectiveTime"
                    },
                    {
                        "identity": "w5",
                        "map": "when.done"
                    }
                ],
                "short": "Clinically Relevant time/time-period for report",
                "comments": "If the diagnostic procedure was performed on the patient, this is the time it was performed. If there are specimens, the diagnostically relevant time can be derived from the specimen collection times, but the specimen information is not always available, and the exact relationship between the specimens and the diagnostically relevant time is not always automatic.",
                "isSummary": true,
                "alias": [
                    "Observation time",
                    "Effective Time"
                ]
            },
            {
                "path": "DiagnosticReport.issued",
                "max": "1",
                "type": [
                    {
                        "code": "instant"
                    }
                ],
                "definition": "The date and time that this version of the report was released from the source diagnostic service.",
                "min": 1,
                "requirements": "Clinicians need to be able to check the date that the report was released.",
                "mapping": [
                    {
                        "identity": "v2",
                        "map": "OBR-22"
                    },
                    {
                        "identity": "rim",
                        "map": "participation[typeCode=VRF or AUT].time"
                    },
                    {
                        "identity": "w5",
                        "map": "when.recorded"
                    }
                ],
                "short": "DateTime this version was released",
                "comments": "May be different from the update time of the resource itself, because that is the status of the record (potentially a secondary copy), not the actual release time of the report.",
                "isSummary": true,
                "alias": [
                    "Date Created",
                    "Date published",
                    "Date Issued"
                ]
            },
            {
                "path": "DiagnosticReport.performer",
                "max": "1",
                "type": [
                    {
                        "code": "Reference",
                        "profile": [
                            "http://hl7.org/fhir/StructureDefinition/Practitioner"
                        ]
                    },
                    {
                        "code": "Reference",
                        "profile": [
                            "http://hl7.org/fhir/StructureDefinition/Organization"
                        ]
                    }
                ],
                "definition": "The diagnostic service that is responsible for issuing the report.",
                "min": 1,
                "requirements": "Need to know whom to contact if there are queries about the results. Also may need to track the source of reports for secondary data analysis.",
                "mapping": [
                    {
                        "identity": "v2",
                        "map": "PRT-8 (where this PRT-4-Participation = \"PO\")"
                    },
                    {
                        "identity": "rim",
                        "map": "participation[typeCode=AUT].role[classCode=ASSIGN].scoper"
                    },
                    {
                        "identity": "w5",
                        "map": "who.witness"
                    }
                ],
                "short": "Responsible Diagnostic Service",
                "comments": "This is not necessarily the source of the atomic data items. It is the entity that takes responsibility for the clinical report.",
                "isSummary": true,
                "alias": [
                    "Laboratory",
                    "Service",
                    "Practitioner",
                    "Department",
                    "Company"
                ]
            },
            {
                "path": "DiagnosticReport.request",
                "max": "*",
                "definition": "Details concerning a test or procedure requested.",
                "min": 0,
                "requirements": "Need to be able to track completion of requests based on reports issued and also to report what diagnostic tests were requested (not always the same as what is delivered).",
                "mapping": [
                    {
                        "identity": "v2",
                        "map": "ORC? OBR-2/3?"
                    },
                    {
                        "identity": "rim",
                        "map": "outboundRelationship[typeCode=FLFS].target"
                    }
                ],
                "short": "What was requested",
                "comments": "Note: Usually there is one test request for each result, however in some circumstances multiple test requests may be represented using a single test result resource. Note that there are also cases where one request leads to multiple reports.",
                "type": [
                    {
                        "code": "Reference",
                        "profile": [
                            "http://hl7.org/fhir/StructureDefinition/DiagnosticOrder"
                        ]
                    },
                    {
                        "code": "Reference",
                        "profile": [
                            "http://hl7.org/fhir/StructureDefinition/ProcedureRequest"
                        ]
                    },
                    {
                        "code": "Reference",
                        "profile": [
                            "http://hl7.org/fhir/StructureDefinition/ReferralRequest"
                        ]
                    }
                ]
            },
            {
                "path": "DiagnosticReport.specimen",
                "max": "*",
                "definition": "Details about the specimens on which this diagnostic report is based.",
                "min": 0,
                "requirements": "Need to be able to report information about the collected specimens on which the report is based.",
                "mapping": [
                    {
                        "identity": "v2",
                        "map": "SPM"
                    },
                    {
                        "identity": "rim",
                        "map": "participation[typeCode=SBJ]"
                    }
                ],
                "short": "Specimens this report is based on",
                "comments": "If the specimen is sufficiently specified with a code in the test result name, then this additional data may be redundant. If there are multiple specimens, these may be represented per Observation or group.",
                "type": [
                    {
                        "code": "Reference",
                        "profile": [
                            "http://hl7.org/fhir/StructureDefinition/Specimen"
                        ]
                    }
                ]
            },
            {
                "path": "DiagnosticReport.result",
                "max": "*",
                "definition": "Observations that are part of this diagnostic report. Observations can be simple name/value pairs (e.g. \"atomic\" results), or they can be grouping observations that include references to other members of the group (e.g. \"panels\").",
                "min": 0,
                "requirements": "Need to support individual results, or report groups of results, where the result grouping is arbitrary, but meaningful. This structure is recursive - observations can contain observations.",
                "mapping": [
                    {
                        "identity": "v2",
                        "map": "OBXs"
                    },
                    {
                        "identity": "rim",
                        "map": "outboundRelationship[typeCode=COMP].target"
                    }
                ],
                "short": "Observations - simple, or complex nested groups",
                "type": [
                    {
                        "code": "Reference",
                        "profile": [
                            "http://hl7.org/fhir/StructureDefinition/Observation"
                        ]
                    }
                ],
                "alias": [
                    "Data",
                    "Atomic Value",
                    "Result",
                    "Atomic result",
                    "Data",
                    "Test",
                    "Analyte",
                    "Battery",
                    "Organizer"
                ]
            },
            {
                "path": "DiagnosticReport.imagingStudy",
                "max": "*",
                "definition": "One or more links to full details of any imaging performed during the diagnostic investigation. Typically, this is imaging performed by DICOM enabled modalities, but this is not required. A fully enabled PACS viewer can use this information to provide views of the source images.",
                "min": 0,
                "comments": "ImagingStudy and ImageObjectStudy and the image element are somewhat overlapping - typically, the list of image references in the image element will also be found in one of the imaging study resources. However each caters to different types of displays for different types of purposes. Neither, either, or both may be provided.",
                "mapping": [
                    {
                        "identity": "rim",
                        "map": "outboundRelationship[typeCode=COMP].target[classsCode=DGIMG, moodCode=EVN]"
                    }
                ],
                "short": "Reference to full details of imaging associated with the diagnostic report",
                "type": [
                    {
                        "code": "Reference",
                        "profile": [
                            "http://hl7.org/fhir/StructureDefinition/ImagingStudy"
                        ]
                    },
                    {
                        "code": "Reference",
                        "profile": [
                            "http://hl7.org/fhir/StructureDefinition/ImagingObjectSelection"
                        ]
                    }
                ]
            },
            {
                "path": "DiagnosticReport.image",
                "max": "*",
                "definition": "A list of key images associated with this report. The images are generally created during the diagnostic process, and may be directly of the patient, or of treated specimens (i.e. slides of interest).",
                "min": 0,
                "requirements": "Many diagnostic services include images in the report as part of their service.",
                "mapping": [
                    {
                        "identity": "v2",
                        "map": "OBX?"
                    },
                    {
                        "identity": "rim",
                        "map": "outboundRelationship[typeCode=COMP].target"
                    }
                ],
                "short": "Key images associated with this report",
                "type": [
                    {
                        "code": "BackboneElement"
                    }
                ],
                "isSummary": true,
                "alias": [
                    "DICOM",
                    "Slides",
                    "Scans"
                ]
            },
            {
                "path": "DiagnosticReport.image.id",
                "max": "1",
                "representation": [
                    "xmlAttr"
                ],
                "definition": "unique id for the element within a resource (for internal references).",
                "min": 0,
                "type": [
                    {
                        "code": "id"
                    }
                ],
                "mapping": [
                    {
                        "identity": "rim",
                        "map": "n/a"
                    }
                ],
                "short": "xml:id (or equivalent in JSON)"
            },
            {
                "path": "DiagnosticReport.image.extension",
                "max": "*",
                "definition": "May be used to represent additional information that is not part of the basic definition of the element. In order to make the use of extensions safe and manageable, there is a strict set of governance  applied to the definition and use of extensions. Though any implementer is allowed to define an extension, there is a set of requirements that SHALL be met as part of the definition of the extension.",
                "min": 0,
                "comments": "There can be no stigma associated with the use of extensions by any application, project, or standard - regardless of the institution or jurisdiction that uses or defines the extensions.  The use of extensions is what allows the FHIR specification to retain a core level of simplicity for everyone.",
                "mapping": [
                    {
                        "identity": "rim",
                        "map": "n/a"
                    }
                ],
                "short": "Additional Content defined by implementations",
                "type": [
                    {
                        "code": "Extension"
                    }
                ],
                "alias": [
                    "extensions",
                    "user content"
                ]
            },
            {
                "path": "DiagnosticReport.image.modifierExtension",
                "max": "*",
                "definition": "May be used to represent additional information that is not part of the basic definition of the element, and that modifies the understanding of the element that contains it. Usually modifier elements provide negation or qualification. In order to make the use of extensions safe and manageable, there is a strict set of governance applied to the definition and use of extensions. Though any implementer is allowed to define an extension, there is a set of requirements that SHALL be met as part of the definition of the extension. Applications processing a resource are required to check for modifier extensions.",
                "min": 0,
                "isModifier": true,
                "comments": "There can be no stigma associated with the use of extensions by any application, project, or standard - regardless of the institution or jurisdiction that uses or defines the extensions.  The use of extensions is what allows the FHIR specification to retain a core level of simplicity for everyone.",
                "mapping": [
                    {
                        "identity": "rim",
                        "map": "N/A"
                    }
                ],
                "short": "Extensions that cannot be ignored",
                "type": [
                    {
                        "code": "Extension"
                    }
                ],
                "alias": [
                    "extensions",
                    "user content",
                    "modifiers"
                ]
            },
            {
                "path": "DiagnosticReport.image.comment",
                "max": "1",
                "definition": "A comment about the image. Typically, this is used to provide an explanation for why the image is included, or to draw the viewer's attention to important features.",
                "min": 0,
                "requirements": "The provider of the report should make a comment about each image included in the report.",
                "mapping": [
                    {
                        "identity": "rim",
                        "map": ".inboundRelationship[typeCode=COMP].source[classCode=OBS, moodCode=EVN, code=\"annotation\"].value"
                    }
                ],
                "short": "Comment about the image (e.g. explanation)",
                "comments": "The comment should be displayed with the image. It would be common for the report to include additional discussion of the image contents in other sections such as the conclusion.",
                "type": [
                    {
                        "code": "string"
                    }
                ]
            },
            {
                "path": "DiagnosticReport.image.link",
                "max": "1",
                "definition": "Reference to the image source.",
                "min": 1,
                "type": [
                    {
                        "code": "Reference",
                        "profile": [
                            "http://hl7.org/fhir/StructureDefinition/Media"
                        ]
                    }
                ],
                "mapping": [
                    {
                        "identity": "rim",
                        "map": ".value.reference"
                    }
                ],
                "short": "Reference to the image source",
                "isSummary": true
            },
            {
                "path": "DiagnosticReport.conclusion",
                "max": "1",
                "type": [
                    {
                        "code": "string"
                    }
                ],
                "definition": "Concise and clinically contextualized narrative interpretation of the diagnostic report.",
                "min": 0,
                "requirements": "Need to be able to provide a conclusion that is not lost among the basic result data.",
                "mapping": [
                    {
                        "identity": "v2",
                        "map": "OBX"
                    },
                    {
                        "identity": "rim",
                        "map": "inboundRelationship[typeCode=\"SPRT\"].source[classCode=OBS, moodCode=EVN, code=LOINC:48767-8].value (type=ST)"
                    }
                ],
                "short": "Clinical Interpretation of test results",
                "comments": "Typically, a report is either [all data, no narrative (e.g. Core lab)] or [a mix of data with some concluding narrative (e.g. Structured Pathology Report, Bone Density)], or [all narrative (e.g. typical imaging report, histopathology)]. In all of these cases, the narrative goes in \"text\".",
                "alias": [
                    "Report"
                ]
            },
            {
                "path": "DiagnosticReport.codedDiagnosis",
                "max": "*",
                "definition": "Codes for the conclusion.",
                "min": 0,
                "type": [
                    {
                        "code": "CodeableConcept"
                    }
                ],
                "mapping": [
                    {
                        "identity": "v2",
                        "map": "OBX"
                    },
                    {
                        "identity": "rim",
                        "map": "inboundRelationship[typeCode=SPRT].source[classCode=OBS, moodCode=EVN, code=LOINC:54531-9].value (type=CD)"
                    }
                ],
                "short": "Codes for the conclusion",
                "binding": {
                    "strength": "example",
                    "description": "Diagnoses codes provided as adjuncts to the report.",
                    "valueSetReference": {
                        "reference": "http://hl7.org/fhir/ValueSet/clinical-findings"
                    }
                }
            },
            {
                "path": "DiagnosticReport.presentedForm",
                "max": "*",
                "definition": "Rich text representation of the entire result as issued by the diagnostic service. Multiple formats are allowed but they SHALL be semantically equivalent.",
                "min": 0,
                "requirements": "Gives Laboratory the ability to provide its own fully formatted report for clinical fidelity.",
                "mapping": [
                    {
                        "identity": "v2",
                        "map": "OBX"
                    },
                    {
                        "identity": "rim",
                        "map": "text (type=ED)"
                    }
                ],
                "short": "Entire report as issued",
                "comments": "\"application/pdf\" is recommended as the most reliable and interoperable in this context.",
                "type": [
                    {
                        "code": "Attachment"
                    }
                ]
            }
        ]
    },
    "publisher": "Health Level Seven International (Orders and Observations)",
    "abstract": false,
    "extension": [
        {
            "valueInteger": 3,
            "url": "http://hl7.org/fhir/StructureDefinition/structuredefinition-fmm"
        }
    ],
    "differential": {
        "element": [
            {
                "path": "DiagnosticReport",
                "max": "*",
                "definition": "The findings and interpretation of diagnostic  tests performed on patients, groups of patients, devices, and locations, and/or specimens derived from these. The report includes clinical context such as requesting and provider information, and some mix of atomic results, images, textual and coded interpretations, and formatted representation of diagnostic reports.",
                "min": 0,
                "comments": "This is intended to capture a single report, and is not suitable for use in displaying summary information that covers multiple reports.  For example, this resource has not been designed for laboratory cumulative reporting formats nor detailed structured reports for sequencing.",
                "mapping": [
                    {
                        "identity": "v2",
                        "map": "ORU -> OBR"
                    },
                    {
                        "identity": "rim",
                        "map": "Observation[classCode=OBS, moodCode=EVN]"
                    },
                    {
                        "identity": "w5",
                        "map": "clinical.diagnostics"
                    }
                ],
                "short": "A Diagnostic report - a combination of request information, atomic results, images, interpretation, as well as formatted reports",
                "type": [
                    {
                        "code": "DomainResource"
                    }
                ],
                "alias": [
                    "Report",
                    "Test",
                    "Result",
                    "Results",
                    "Labs",
                    "Laboratory"
                ]
            },
            {
                "path": "DiagnosticReport.identifier",
                "max": "*",
                "definition": "The local ID assigned to the report by the order filler, usually by the Information System of the diagnostic service provider.",
                "min": 0,
                "requirements": "Need to know what identifier to use when making queries about this report from the source laboratory, and for linking to the report outside FHIR context.",
                "mapping": [
                    {
                        "identity": "v2",
                        "map": "OBR-51"
                    },
                    {
                        "identity": "rim",
                        "map": "id"
                    },
                    {
                        "identity": "w5",
                        "map": "id"
                    }
                ],
                "short": "Id for external references to this report",
                "type": [
                    {
                        "code": "Identifier"
                    }
                ],
                "isSummary": true,
                "alias": [
                    "ReportID"
                ]
            },
            {
                "path": "DiagnosticReport.status",
                "min": 1,
                "comments": "This is labeled as \"Is Modifier\" because applications need to take appropriate action if a report is withdrawn.",
                "short": "registered | partial | final | corrected | appended | cancelled | entered-in-error",
                "type": [
                    {
                        "code": "code"
                    }
                ],
                "binding": {
                    "strength": "required",
                    "description": "The status of the diagnostic report as a whole.",
                    "valueSetReference": {
                        "reference": "http://hl7.org/fhir/ValueSet/diagnostic-report-status"
                    }
                },
                "isSummary": true,
                "max": "1",
                "definition": "The status of the diagnostic report as a whole.",
                "mapping": [
                    {
                        "identity": "v2",
                        "map": "OBR-25 (not 1:1 mapping)"
                    },
                    {
                        "identity": "rim",
                        "map": "statusCode  Note: final and amended are distinguished by whether observation is the subject of a ControlAct event of type \"revise\""
                    },
                    {
                        "identity": "w5",
                        "map": "status"
                    }
                ],
                "requirements": "Diagnostic services routinely issue provisional/incomplete reports, and sometimes withdraw previously released reports.",
                "isModifier": true
            },
            {
                "path": "DiagnosticReport.category",
                "max": "1",
                "definition": "A code that classifies the clinical discipline, department or diagnostic service that created the report (e.g. cardiology, biochemistry, hematology, MRI). This is used for searching, sorting and display purposes.",
                "min": 0,
                "comments": "The level of granularity is defined by the category concepts in the value set. More fine-grained filtering can be performed using the metadata and/or terminology hierarchy in DiagnosticReport.code.",
                "mapping": [
                    {
                        "identity": "v2",
                        "map": "OBR-24"
                    },
                    {
                        "identity": "rim",
                        "map": "inboundRelationship[typeCode=COMP].source[classCode=LIST, moodCode=EVN, code < LabService].code"
                    },
                    {
                        "identity": "w5",
                        "map": "class"
                    }
                ],
                "short": "Service category",
                "type": [
                    {
                        "code": "CodeableConcept"
                    }
                ],
                "isSummary": true,
                "binding": {
                    "strength": "example",
                    "description": "Codes for diagnostic service sections.",
                    "valueSetReference": {
                        "reference": "http://hl7.org/fhir/ValueSet/diagnostic-service-sections"
                    }
                },
                "alias": [
                    "Department",
                    "Sub-department",
                    "service",
                    "discipline"
                ]
            },
            {
                "path": "DiagnosticReport.code",
                "max": "1",
                "definition": "A code or name that describes this diagnostic report.",
                "min": 1,
                "type": [
                    {
                        "code": "CodeableConcept"
                    }
                ],
                "mapping": [
                    {
                        "identity": "v2",
                        "map": "OBR-4 (HL7 v2 doesn't provide an easy way to indicate both the ordered test and the performed panel)"
                    },
                    {
                        "identity": "rim",
                        "map": "code"
                    },
                    {
                        "identity": "w5",
                        "map": "what"
                    }
                ],
                "short": "Name/Code for this diagnostic report",
                "isSummary": true,
                "binding": {
                    "strength": "preferred",
                    "description": "Codes that describe Diagnostic Reports.",
                    "valueSetReference": {
                        "reference": "http://hl7.org/fhir/ValueSet/report-codes"
                    }
                }
            },
            {
                "path": "DiagnosticReport.subject",
                "max": "1",
                "definition": "The subject of the report. Usually, but not always, this is a patient. However diagnostic services also perform analyses on specimens collected from a variety of other sources.",
                "min": 1,
                "requirements": "SHALL know the subject context.",
                "mapping": [
                    {
                        "identity": "v2",
                        "map": "PID-3 (no HL7 v2 mapping for Group or Device)"
                    },
                    {
                        "identity": "rim",
                        "map": "participation[typeCode=SBJ]"
                    },
                    {
                        "identity": "w5",
                        "map": "who.focus"
                    }
                ],
                "short": "The subject of the report, usually, but not always, the patient",
                "type": [
                    {
                        "code": "Reference",
                        "profile": [
                            "http://hl7.org/fhir/StructureDefinition/Patient"
                        ]
                    },
                    {
                        "code": "Reference",
                        "profile": [
                            "http://hl7.org/fhir/StructureDefinition/Group"
                        ]
                    },
                    {
                        "code": "Reference",
                        "profile": [
                            "http://hl7.org/fhir/StructureDefinition/Device"
                        ]
                    },
                    {
                        "code": "Reference",
                        "profile": [
                            "http://hl7.org/fhir/StructureDefinition/Location"
                        ]
                    }
                ],
                "isSummary": true,
                "alias": [
                    "Patient"
                ]
            },
            {
                "path": "DiagnosticReport.encounter",
                "max": "1",
                "definition": "The link to the health care event (encounter) when the order was made.",
                "min": 0,
                "type": [
                    {
                        "code": "Reference",
                        "profile": [
                            "http://hl7.org/fhir/StructureDefinition/Encounter"
                        ]
                    }
                ],
                "mapping": [
                    {
                        "identity": "v2",
                        "map": "PV1-19"
                    },
                    {
                        "identity": "rim",
                        "map": "inboundRelationship[typeCode=COMP].source[classCode=ENC, moodCode=EVN]"
                    },
                    {
                        "identity": "w5",
                        "map": "context"
                    }
                ],
                "short": "Health care event when test ordered",
                "isSummary": true
            },
            {
                "path": "DiagnosticReport.effective[x]",
                "max": "1",
                "type": [
                    {
                        "code": "dateTime"
                    },
                    {
                        "code": "Period"
                    }
                ],
                "definition": "The time or time-period the observed values are related to. When the subject of the report is a patient, this is usually either the time of the procedure or of specimen collection(s), but very often the source of the date/time is not known, only the date/time itself.",
                "min": 1,
                "requirements": "Need to know where in the patient history to file/present this report.",
                "mapping": [
                    {
                        "identity": "v2",
                        "map": "OBR-7"
                    },
                    {
                        "identity": "rim",
                        "map": "effectiveTime"
                    },
                    {
                        "identity": "w5",
                        "map": "when.done"
                    }
                ],
                "short": "Clinically Relevant time/time-period for report",
                "comments": "If the diagnostic procedure was performed on the patient, this is the time it was performed. If there are specimens, the diagnostically relevant time can be derived from the specimen collection times, but the specimen information is not always available, and the exact relationship between the specimens and the diagnostically relevant time is not always automatic.",
                "isSummary": true,
                "alias": [
                    "Observation time",
                    "Effective Time"
                ]
            },
            {
                "path": "DiagnosticReport.issued",
                "max": "1",
                "type": [
                    {
                        "code": "instant"
                    }
                ],
                "definition": "The date and time that this version of the report was released from the source diagnostic service.",
                "min": 1,
                "requirements": "Clinicians need to be able to check the date that the report was released.",
                "mapping": [
                    {
                        "identity": "v2",
                        "map": "OBR-22"
                    },
                    {
                        "identity": "rim",
                        "map": "participation[typeCode=VRF or AUT].time"
                    },
                    {
                        "identity": "w5",
                        "map": "when.recorded"
                    }
                ],
                "short": "DateTime this version was released",
                "comments": "May be different from the update time of the resource itself, because that is the status of the record (potentially a secondary copy), not the actual release time of the report.",
                "isSummary": true,
                "alias": [
                    "Date Created",
                    "Date published",
                    "Date Issued"
                ]
            },
            {
                "path": "DiagnosticReport.performer",
                "max": "1",
                "type": [
                    {
                        "code": "Reference",
                        "profile": [
                            "http://hl7.org/fhir/StructureDefinition/Practitioner"
                        ]
                    },
                    {
                        "code": "Reference",
                        "profile": [
                            "http://hl7.org/fhir/StructureDefinition/Organization"
                        ]
                    }
                ],
                "definition": "The diagnostic service that is responsible for issuing the report.",
                "min": 1,
                "requirements": "Need to know whom to contact if there are queries about the results. Also may need to track the source of reports for secondary data analysis.",
                "mapping": [
                    {
                        "identity": "v2",
                        "map": "PRT-8 (where this PRT-4-Participation = \"PO\")"
                    },
                    {
                        "identity": "rim",
                        "map": "participation[typeCode=AUT].role[classCode=ASSIGN].scoper"
                    },
                    {
                        "identity": "w5",
                        "map": "who.witness"
                    }
                ],
                "short": "Responsible Diagnostic Service",
                "comments": "This is not necessarily the source of the atomic data items. It is the entity that takes responsibility for the clinical report.",
                "isSummary": true,
                "alias": [
                    "Laboratory",
                    "Service",
                    "Practitioner",
                    "Department",
                    "Company"
                ]
            },
            {
                "path": "DiagnosticReport.request",
                "max": "*",
                "definition": "Details concerning a test or procedure requested.",
                "min": 0,
                "requirements": "Need to be able to track completion of requests based on reports issued and also to report what diagnostic tests were requested (not always the same as what is delivered).",
                "mapping": [
                    {
                        "identity": "v2",
                        "map": "ORC? OBR-2/3?"
                    },
                    {
                        "identity": "rim",
                        "map": "outboundRelationship[typeCode=FLFS].target"
                    }
                ],
                "short": "What was requested",
                "comments": "Note: Usually there is one test request for each result, however in some circumstances multiple test requests may be represented using a single test result resource. Note that there are also cases where one request leads to multiple reports.",
                "type": [
                    {
                        "code": "Reference",
                        "profile": [
                            "http://hl7.org/fhir/StructureDefinition/DiagnosticOrder"
                        ]
                    },
                    {
                        "code": "Reference",
                        "profile": [
                            "http://hl7.org/fhir/StructureDefinition/ProcedureRequest"
                        ]
                    },
                    {
                        "code": "Reference",
                        "profile": [
                            "http://hl7.org/fhir/StructureDefinition/ReferralRequest"
                        ]
                    }
                ]
            },
            {
                "path": "DiagnosticReport.specimen",
                "max": "*",
                "definition": "Details about the specimens on which this diagnostic report is based.",
                "min": 0,
                "requirements": "Need to be able to report information about the collected specimens on which the report is based.",
                "mapping": [
                    {
                        "identity": "v2",
                        "map": "SPM"
                    },
                    {
                        "identity": "rim",
                        "map": "participation[typeCode=SBJ]"
                    }
                ],
                "short": "Specimens this report is based on",
                "comments": "If the specimen is sufficiently specified with a code in the test result name, then this additional data may be redundant. If there are multiple specimens, these may be represented per Observation or group.",
                "type": [
                    {
                        "code": "Reference",
                        "profile": [
                            "http://hl7.org/fhir/StructureDefinition/Specimen"
                        ]
                    }
                ]
            },
            {
                "path": "DiagnosticReport.result",
                "max": "*",
                "definition": "Observations that are part of this diagnostic report. Observations can be simple name/value pairs (e.g. \"atomic\" results), or they can be grouping observations that include references to other members of the group (e.g. \"panels\").",
                "min": 0,
                "requirements": "Need to support individual results, or report groups of results, where the result grouping is arbitrary, but meaningful. This structure is recursive - observations can contain observations.",
                "mapping": [
                    {
                        "identity": "v2",
                        "map": "OBXs"
                    },
                    {
                        "identity": "rim",
                        "map": "outboundRelationship[typeCode=COMP].target"
                    }
                ],
                "short": "Observations - simple, or complex nested groups",
                "type": [
                    {
                        "code": "Reference",
                        "profile": [
                            "http://hl7.org/fhir/StructureDefinition/Observation"
                        ]
                    }
                ],
                "alias": [
                    "Data",
                    "Atomic Value",
                    "Result",
                    "Atomic result",
                    "Data",
                    "Test",
                    "Analyte",
                    "Battery",
                    "Organizer"
                ]
            },
            {
                "path": "DiagnosticReport.imagingStudy",
                "max": "*",
                "definition": "One or more links to full details of any imaging performed during the diagnostic investigation. Typically, this is imaging performed by DICOM enabled modalities, but this is not required. A fully enabled PACS viewer can use this information to provide views of the source images.",
                "min": 0,
                "comments": "ImagingStudy and ImageObjectStudy and the image element are somewhat overlapping - typically, the list of image references in the image element will also be found in one of the imaging study resources. However each caters to different types of displays for different types of purposes. Neither, either, or both may be provided.",
                "mapping": [
                    {
                        "identity": "rim",
                        "map": "outboundRelationship[typeCode=COMP].target[classsCode=DGIMG, moodCode=EVN]"
                    }
                ],
                "short": "Reference to full details of imaging associated with the diagnostic report",
                "type": [
                    {
                        "code": "Reference",
                        "profile": [
                            "http://hl7.org/fhir/StructureDefinition/ImagingStudy"
                        ]
                    },
                    {
                        "code": "Reference",
                        "profile": [
                            "http://hl7.org/fhir/StructureDefinition/ImagingObjectSelection"
                        ]
                    }
                ]
            },
            {
                "path": "DiagnosticReport.image",
                "max": "*",
                "definition": "A list of key images associated with this report. The images are generally created during the diagnostic process, and may be directly of the patient, or of treated specimens (i.e. slides of interest).",
                "min": 0,
                "requirements": "Many diagnostic services include images in the report as part of their service.",
                "mapping": [
                    {
                        "identity": "v2",
                        "map": "OBX?"
                    },
                    {
                        "identity": "rim",
                        "map": "outboundRelationship[typeCode=COMP].target"
                    }
                ],
                "short": "Key images associated with this report",
                "type": [
                    {
                        "code": "BackboneElement"
                    }
                ],
                "isSummary": true,
                "alias": [
                    "DICOM",
                    "Slides",
                    "Scans"
                ]
            },
            {
                "path": "DiagnosticReport.image.comment",
                "max": "1",
                "definition": "A comment about the image. Typically, this is used to provide an explanation for why the image is included, or to draw the viewer's attention to important features.",
                "min": 0,
                "requirements": "The provider of the report should make a comment about each image included in the report.",
                "mapping": [
                    {
                        "identity": "rim",
                        "map": ".inboundRelationship[typeCode=COMP].source[classCode=OBS, moodCode=EVN, code=\"annotation\"].value"
                    }
                ],
                "short": "Comment about the image (e.g. explanation)",
                "comments": "The comment should be displayed with the image. It would be common for the report to include additional discussion of the image contents in other sections such as the conclusion.",
                "type": [
                    {
                        "code": "string"
                    }
                ]
            },
            {
                "path": "DiagnosticReport.image.link",
                "max": "1",
                "definition": "Reference to the image source.",
                "min": 1,
                "type": [
                    {
                        "code": "Reference",
                        "profile": [
                            "http://hl7.org/fhir/StructureDefinition/Media"
                        ]
                    }
                ],
                "mapping": [
                    {
                        "identity": "rim",
                        "map": ".value.reference"
                    }
                ],
                "short": "Reference to the image source",
                "isSummary": true
            },
            {
                "path": "DiagnosticReport.conclusion",
                "max": "1",
                "type": [
                    {
                        "code": "string"
                    }
                ],
                "definition": "Concise and clinically contextualized narrative interpretation of the diagnostic report.",
                "min": 0,
                "requirements": "Need to be able to provide a conclusion that is not lost among the basic result data.",
                "mapping": [
                    {
                        "identity": "v2",
                        "map": "OBX"
                    },
                    {
                        "identity": "rim",
                        "map": "inboundRelationship[typeCode=\"SPRT\"].source[classCode=OBS, moodCode=EVN, code=LOINC:48767-8].value (type=ST)"
                    }
                ],
                "short": "Clinical Interpretation of test results",
                "comments": "Typically, a report is either [all data, no narrative (e.g. Core lab)] or [a mix of data with some concluding narrative (e.g. Structured Pathology Report, Bone Density)], or [all narrative (e.g. typical imaging report, histopathology)]. In all of these cases, the narrative goes in \"text\".",
                "alias": [
                    "Report"
                ]
            },
            {
                "path": "DiagnosticReport.codedDiagnosis",
                "max": "*",
                "definition": "Codes for the conclusion.",
                "min": 0,
                "type": [
                    {
                        "code": "CodeableConcept"
                    }
                ],
                "mapping": [
                    {
                        "identity": "v2",
                        "map": "OBX"
                    },
                    {
                        "identity": "rim",
                        "map": "inboundRelationship[typeCode=SPRT].source[classCode=OBS, moodCode=EVN, code=LOINC:54531-9].value (type=CD)"
                    }
                ],
                "short": "Codes for the conclusion",
                "binding": {
                    "strength": "example",
                    "description": "Diagnoses codes provided as adjuncts to the report.",
                    "valueSetReference": {
                        "reference": "http://hl7.org/fhir/ValueSet/clinical-findings"
                    }
                }
            },
            {
                "path": "DiagnosticReport.presentedForm",
                "max": "*",
                "definition": "Rich text representation of the entire result as issued by the diagnostic service. Multiple formats are allowed but they SHALL be semantically equivalent.",
                "min": 0,
                "requirements": "Gives Laboratory the ability to provide its own fully formatted report for clinical fidelity.",
                "mapping": [
                    {
                        "identity": "v2",
                        "map": "OBX"
                    },
                    {
                        "identity": "rim",
                        "map": "text (type=ED)"
                    }
                ],
                "short": "Entire report as issued",
                "comments": "\"application/pdf\" is recommended as the most reliable and interoperable in this context.",
                "type": [
                    {
                        "code": "Attachment"
                    }
                ]
            }
        ]
    },
    "resourceType": "StructureDefinition",
    "description": "Base StructureDefinition for DiagnosticReport Resource",
    "url": "http://hl7.org/fhir/StructureDefinition/DiagnosticReport",
    "kind": "resource",
    "contact": [
        {
            "telecom": [
                {
                    "system": "other",
                    "value": "http://hl7.org/fhir"
                }
            ]
        },
        {
            "telecom": [
                {
                    "system": "other",
                    "value": "http://www.hl7.org/Special/committees/orders/index.cfm"
                }
            ]
        }
    ],
    "mapping": [
        {
            "identity": "v2",
            "name": "HL7 v2",
            "uri": "http://hl7.org/v2"
        },
        {
            "identity": "rim",
            "name": "RIM",
            "uri": "http://hl7.org/v3"
        },
        {
            "identity": "w5",
            "name": "W5 Mapping",
            "uri": "http://hl7.org/fhir/w5"
        }
    ],
    "status": "draft",
    "requirements": "To support reporting for any diagnostic report into a clinical data repository.",
    "base": "http://hl7.org/fhir/StructureDefinition/DomainResource",
    "name": "DiagnosticReport",
    "id": "DiagnosticReport",
    "meta": {
        "lastUpdated": "2015-10-24T07:41:03.495+11:00"
    },
    "fhirVersion": "1.0.2",
    "date": "2015-10-24T07:41:03+11:00"
}