{
    "id": "DomainResource",
    "date": "2015-10-24T07:41:03+11:00",
    "differential": {
        "element": [
            {
                "type": [
                    {
                        "code": "Resource"
                    }
                ],
                "constraint": [
                    {
                        "human": "If a resource is contained in another resource, it SHALL NOT have a meta.versionId or a meta.lastUpdated",
                        "severity": "error",
                        "xpath": "not(exists(f:contained/*/f:meta/f:versionId)) and not(exists(f:contained/*/f:meta/f:lastUpdated))",
                        "key": "dom-4"
                    },
                    {
                        "human": "If the resource is contained in another resource, it SHALL be referred to from elsewhere in the resource",
                        "severity": "error",
                        "xpath": "not(exists(for $id in f:contained/*/@id return $id[not(ancestor::f:contained/parent::*/descendant::f:reference/@value=concat('#', $id))]))",
                        "key": "dom-3"
                    },
                    {
                        "human": "If the resource is contained in another resource, it SHALL NOT contain nested Resources",
                        "severity": "error",
                        "xpath": "not(parent::f:contained and f:contained)",
                        "key": "dom-2"
                    },
                    {
                        "human": "If the resource is contained in another resource, it SHALL NOT contain any narrative",
                        "severity": "error",
                        "xpath": "not(parent::f:contained and f:text)",
                        "key": "dom-1"
                    }
                ],
                "max": "*",
                "definition": "A resource that includes narrative, extensions, and contained resources.",
                "short": "A resource with narrative, extensions, and contained resources",
                "min": 0,
                "mapping": [
                    {
                        "map": "Entity. Role, or Act",
                        "identity": "rim"
                    }
                ],
                "path": "DomainResource"
            },
            {
                "condition": [
                    "dom-1"
                ],
                "type": [
                    {
                        "code": "Narrative"
                    }
                ],
                "max": "1",
                "definition": "A human-readable narrative that contains a summary of the resource, and may be used to represent the content of the resource to a human. The narrative need not encode all the structured data, but is required to contain sufficient detail to make it \"clinically safe\" for a human to just read the narrative. Resource definitions may define what content should be represented in the narrative to ensure clinical safety.",
                "short": "Text summary of the resource, for human interpretation",
                "min": 0,
                "alias": [
                    "narrative",
                    "html",
                    "xhtml",
                    "display"
                ],
                "comments": "Contained resources do not have narrative. Resources that are not contained SHOULD have a narrative.",
                "path": "DomainResource.text",
                "mapping": [
                    {
                        "map": "Act.text?",
                        "identity": "rim"
                    }
                ]
            },
            {
                "type": [
                    {
                        "code": "Resource"
                    }
                ],
                "max": "*",
                "definition": "These resources do not have an independent existence apart from the resource that contains them - they cannot be identified independently, and nor can they have their own independent transaction scope.",
                "short": "Contained, inline Resources",
                "min": 0,
                "alias": [
                    "inline resources",
                    "anonymous resources",
                    "contained resources"
                ],
                "comments": "This should never be done when the content can be identified properly, as once identification is lost, it is extremely difficult (and context dependent) to restore it again.",
                "path": "DomainResource.contained",
                "mapping": [
                    {
                        "map": "N/A",
                        "identity": "rim"
                    }
                ]
            },
            {
                "type": [
                    {
                        "code": "Extension"
                    }
                ],
                "max": "*",
                "definition": "May be used to represent additional information that is not part of the basic definition of the resource. In order to make the use of extensions safe and manageable, there is a strict set of governance  applied to the definition and use of extensions. Though any implementer is allowed to define an extension, there is a set of requirements that SHALL be met as part of the definition of the extension.",
                "short": "Additional Content defined by implementations",
                "min": 0,
                "alias": [
                    "extensions",
                    "user content"
                ],
                "comments": "There can be no stigma associated with the use of extensions by any application, project, or standard - regardless of the institution or jurisdiction that uses or defines the extensions.  The use of extensions is what allows the FHIR specification to retain a core level of simplicity for everyone.",
                "path": "DomainResource.extension",
                "mapping": [
                    {
                        "map": "N/A",
                        "identity": "rim"
                    }
                ]
            },
            {
                "type": [
                    {
                        "code": "Extension"
                    }
                ],
                "max": "*",
                "definition": "May be used to represent additional information that is not part of the basic definition of the resource, and that modifies the understanding of the element that contains it. Usually modifier elements provide negation or qualification. In order to make the use of extensions safe and manageable, there is a strict set of governance applied to the definition and use of extensions. Though any implementer is allowed to define an extension, there is a set of requirements that SHALL be met as part of the definition of the extension. Applications processing a resource are required to check for modifier extensions.",
                "isModifier": true,
                "short": "Extensions that cannot be ignored",
                "min": 0,
                "alias": [
                    "extensions",
                    "user content"
                ],
                "comments": "There can be no stigma associated with the use of extensions by any application, project, or standard - regardless of the institution or jurisdiction that uses or defines the extensions.  The use of extensions is what allows the FHIR specification to retain a core level of simplicity for everyone.",
                "path": "DomainResource.modifierExtension",
                "mapping": [
                    {
                        "map": "N/A",
                        "identity": "rim"
                    }
                ]
            }
        ]
    },
    "name": "DomainResource",
    "abstract": true,
    "status": "draft",
    "kind": "resource",
    "extension": [
        {
            "url": "http://hl7.org/fhir/StructureDefinition/structuredefinition-fmm",
            "valueInteger": 2
        }
    ],
    "snapshot": {
        "element": [
            {
                "type": [
                    {
                        "code": "Resource"
                    }
                ],
                "constraint": [
                    {
                        "human": "If a resource is contained in another resource, it SHALL NOT have a meta.versionId or a meta.lastUpdated",
                        "severity": "error",
                        "xpath": "not(exists(f:contained/*/f:meta/f:versionId)) and not(exists(f:contained/*/f:meta/f:lastUpdated))",
                        "key": "dom-4"
                    },
                    {
                        "human": "If the resource is contained in another resource, it SHALL be referred to from elsewhere in the resource",
                        "severity": "error",
                        "xpath": "not(exists(for $id in f:contained/*/@id return $id[not(ancestor::f:contained/parent::*/descendant::f:reference/@value=concat('#', $id))]))",
                        "key": "dom-3"
                    },
                    {
                        "human": "If the resource is contained in another resource, it SHALL NOT contain nested Resources",
                        "severity": "error",
                        "xpath": "not(parent::f:contained and f:contained)",
                        "key": "dom-2"
                    },
                    {
                        "human": "If the resource is contained in another resource, it SHALL NOT contain any narrative",
                        "severity": "error",
                        "xpath": "not(parent::f:contained and f:text)",
                        "key": "dom-1"
                    }
                ],
                "max": "*",
                "definition": "A resource that includes narrative, extensions, and contained resources.",
                "short": "A resource with narrative, extensions, and contained resources",
                "min": 0,
                "mapping": [
                    {
                        "map": "Entity. Role, or Act",
                        "identity": "rim"
                    }
                ],
                "path": "DomainResource"
            },
            {
                "type": [
                    {
                        "code": "id"
                    }
                ],
                "max": "1",
                "definition": "The logical id of the resource, as used in the URL for the resource. Once assigned, this value never changes.",
                "short": "Logical id of this artifact",
                "min": 0,
                "comments": "The only time that a resource does not have an id is when it is being submitted to the server using a create operation. Bundles always have an id, though it is usually a generated UUID.",
                "path": "DomainResource.id",
                "isSummary": true
            },
            {
                "type": [
                    {
                        "code": "Meta"
                    }
                ],
                "max": "1",
                "definition": "The metadata about the resource. This is content that is maintained by the infrastructure. Changes to the content may not always be associated with version changes to the resource.",
                "short": "Metadata about the resource",
                "min": 0,
                "isSummary": true,
                "path": "DomainResource.meta"
            },
            {
                "type": [
                    {
                        "code": "uri"
                    }
                ],
                "max": "1",
                "definition": "A reference to a set of rules that were followed when the resource was constructed, and which must be understood when processing the content.",
                "isModifier": true,
                "short": "A set of rules under which this content was created",
                "min": 0,
                "comments": "Asserting this rule set restricts the content to be only understood by a limited set of trading partners. This inherently limits the usefulness of the data in the long term. However, the existing health eco-system is highly fractured, and not yet ready to define, collect, and exchange data in a generally computable sense. Wherever possible, implementers and/or specification writers should avoid using this element as much as possible.",
                "path": "DomainResource.implicitRules",
                "isSummary": true
            },
            {
                "type": [
                    {
                        "code": "code"
                    }
                ],
                "max": "1",
                "definition": "The base language in which the resource is written.",
                "short": "Language of the resource content",
                "min": 0,
                "binding": {
                    "description": "A human language.",
                    "strength": "required",
                    "valueSetUri": "http://tools.ietf.org/html/bcp47"
                },
                "comments": "Language is provided to support indexing and accessibility (typically, services such as text to speech use the language tag). The html language tag in the narrative applies  to the narrative. The language tag on the resource may be used to specify the language of other presentations generated from the data in the resource  Not all the content has to be in the base language. The Resource.language should not be assumed to apply to the narrative automatically. If a language is specified, it should it also be specified on the div element in the html (see rules in HTML5 for information about the relationship between xml:lang and the html lang attribute).",
                "path": "DomainResource.language"
            },
            {
                "condition": [
                    "dom-1"
                ],
                "type": [
                    {
                        "code": "Narrative"
                    }
                ],
                "max": "1",
                "definition": "A human-readable narrative that contains a summary of the resource, and may be used to represent the content of the resource to a human. The narrative need not encode all the structured data, but is required to contain sufficient detail to make it \"clinically safe\" for a human to just read the narrative. Resource definitions may define what content should be represented in the narrative to ensure clinical safety.",
                "short": "Text summary of the resource, for human interpretation",
                "min": 0,
                "alias": [
                    "narrative",
                    "html",
                    "xhtml",
                    "display"
                ],
                "comments": "Contained resources do not have narrative. Resources that are not contained SHOULD have a narrative.",
                "path": "DomainResource.text",
                "mapping": [
                    {
                        "map": "Act.text?",
                        "identity": "rim"
                    }
                ]
            },
            {
                "type": [
                    {
                        "code": "Resource"
                    }
                ],
                "max": "*",
                "definition": "These resources do not have an independent existence apart from the resource that contains them - they cannot be identified independently, and nor can they have their own independent transaction scope.",
                "short": "Contained, inline Resources",
                "min": 0,
                "alias": [
                    "inline resources",
                    "anonymous resources",
                    "contained resources"
                ],
                "comments": "This should never be done when the content can be identified properly, as once identification is lost, it is extremely difficult (and context dependent) to restore it again.",
                "path": "DomainResource.contained",
                "mapping": [
                    {
                        "map": "N/A",
                        "identity": "rim"
                    }
                ]
            },
            {
                "type": [
                    {
                        "code": "Extension"
                    }
                ],
                "max": "*",
                "definition": "May be used to represent additional information that is not part of the basic definition of the resource. In order to make the use of extensions safe and manageable, there is a strict set of governance  applied to the definition and use of extensions. Though any implementer is allowed to define an extension, there is a set of requirements that SHALL be met as part of the definition of the extension.",
                "short": "Additional Content defined by implementations",
                "min": 0,
                "alias": [
                    "extensions",
                    "user content"
                ],
                "comments": "There can be no stigma associated with the use of extensions by any application, project, or standard - regardless of the institution or jurisdiction that uses or defines the extensions.  The use of extensions is what allows the FHIR specification to retain a core level of simplicity for everyone.",
                "path": "DomainResource.extension",
                "mapping": [
                    {
                        "map": "N/A",
                        "identity": "rim"
                    }
                ]
            },
            {
                "type": [
                    {
                        "code": "Extension"
                    }
                ],
                "max": "*",
                "definition": "May be used to represent additional information that is not part of the basic definition of the resource, and that modifies the understanding of the element that contains it. Usually modifier elements provide negation or qualification. In order to make the use of extensions safe and manageable, there is a strict set of governance applied to the definition and use of extensions. Though any implementer is allowed to define an extension, there is a set of requirements that SHALL be met as part of the definition of the extension. Applications processing a resource are required to check for modifier extensions.",
                "isModifier": true,
                "short": "Extensions that cannot be ignored",
                "min": 0,
                "alias": [
                    "extensions",
                    "user content"
                ],
                "comments": "There can be no stigma associated with the use of extensions by any application, project, or standard - regardless of the institution or jurisdiction that uses or defines the extensions.  The use of extensions is what allows the FHIR specification to retain a core level of simplicity for everyone.",
                "path": "DomainResource.modifierExtension",
                "mapping": [
                    {
                        "map": "N/A",
                        "identity": "rim"
                    }
                ]
            }
        ]
    },
    "description": "Base StructureDefinition for DomainResource Resource",
    "url": "http://hl7.org/fhir/StructureDefinition/DomainResource",
    "fhirVersion": "1.0.2",
    "base": "http://hl7.org/fhir/StructureDefinition/Resource",
    "mapping": [
        {
            "uri": "http://hl7.org/v3",
            "identity": "rim",
            "name": "RIM"
        }
    ],
    "resourceType": "StructureDefinition",
    "meta": {
        "lastUpdated": "2015-10-24T07:41:03.495+11:00"
    },
    "contact": [
        {
            "telecom": [
                {
                    "value": "http://hl7.org/fhir",
                    "system": "other"
                }
            ]
        },
        {
            "telecom": [
                {
                    "value": "http://www.hl7.org/Special/committees/fiwg/index.cfm",
                    "system": "other"
                }
            ]
        }
    ],
    "publisher": "Health Level Seven International (FHIR Infrastructure)"
}